satchel/__init__.py
satchel/aggregate.py
satchel/iterable.py
satchel/py.typed
pysatchel-0.3.1.dist-info/WHEEL
pysatchel-0.3.1.dist-info/METADATA
pysatchel-0.3.1.dist-info/RECORD
