Metadata-Version: 2.1
Name: pysatchel
Version: 0.3.1
Summary: Satchel is a compendium of pure python functions to carry with you and get things done.
Home-page: https://github.com/theelderbeever/satchel
License: MIT
Author: Taylor Beever
Author-email: taybeever@gmail.com
Requires-Python: >=3.8,<4.0
Classifier: License :: OSI Approved :: MIT License
Classifier: Programming Language :: Python :: 3
Classifier: Programming Language :: Python :: 3.10
Classifier: Programming Language :: Python :: 3.8
Classifier: Programming Language :: Python :: 3.9
Project-URL: Repository, https://github.com/theelderbeever/satchel
